LICENSE
MANIFEST.in
NEWS
README.rst
ez_setup.py
setup.cfg
setup.py
thunder/__init__.py
thunder/exceptions.py
thunder/fields.py
thunder/info.py
thunder/store.py
thunder.egg-info/PKG-INFO
thunder.egg-info/SOURCES.txt
thunder.egg-info/dependency_links.txt
thunder.egg-info/not-zip-safe
thunder.egg-info/top_level.txt
thunder/tests/__init__.py
thunder/tests/test_simple.py