Metadata-Version: 1.0
Name: thunder
Version: 0.1.0
Summary: Thunder is an object-relational mapper (ORM) for Python
Home-page: https://github.com/jdahlin/thunder
Author: Johan Dahlin
Author-email: johan@gnome.org
License: LGPL
Download-URL: https://github.com/jdahlin/thunder/downloads
Platform: UNKNOWN
Classifier: Development Status :: 3 - Alpha
Classifier: Intended Audience :: Developers
Classifier: License :: OSI Approved :: GNU Library or Lesser General Public License (LGPL)
Classifier: Programming Language :: Python
Classifier: Topic :: Database
Classifier: Topic :: Database :: Front-Ends
Classifier: Topic :: Software Development :: Libraries :: Python Modules
